standup_face_recognition/MTCNN_detector.py
standup_face_recognition/__init__.py
standup_face_recognition/face_recognition.py
standup_face_recognition/main.py
standup_face_recognition/team_embedding_webcam.pth
standup_face_recognition/utils.py
standup_face_recognition/facenet_pytorch/__init__.py
standup_face_recognition/facenet_pytorch/test.py
standup_face_recognition/facenet_pytorch/data/__init__.py
standup_face_recognition/facenet_pytorch/data/onet.pt
standup_face_recognition/facenet_pytorch/data/pnet.pt
standup_face_recognition/facenet_pytorch/data/rnet.pt
standup_face_recognition/facenet_pytorch/models/__init__.py
standup_face_recognition/facenet_pytorch/models/inception_resnet_v1.py
standup_face_recognition/facenet_pytorch/models/mtcnn.py
standup_face_recognition/facenet_pytorch/models/utils/__init__.py
standup_face_recognition/facenet_pytorch/models/utils/detect_face.py
standup_face_recognition/facenet_pytorch/models/utils/download.py
standup_face_recognition/facenet_pytorch/models/utils/tensorflow2pytorch.py
standup_face_recognition/facenet_pytorch/models/utils/training.py
standup_face_recognition-1.9.dist-info/METADATA
standup_face_recognition-1.9.dist-info/WHEEL
standup_face_recognition-1.9.dist-info/entry_points.txt
standup_face_recognition-1.9.dist-info/top_level.txt
standup_face_recognition-1.9.dist-info/RECORD
